Workbook

Sheet Custos
A1: SKU | B1: Custo do Fornecedor
A2: DEMO-001 | B2: 290
A3: DEMO-002 | B3: 235
A4: DEMO-003 | B4: 142
A5: DEMO-004 | B5: 100
A6: DEMO-005 | B6: 165
A7: DEMO-006 | B7: 62

Sheet Comentários
A1: Demo: resultado esperado do auditor
A2: Todos os dados deste arquivo e do anuncios_ml.csv são fictícios, criados apenas para demonstração.
A3: Regra do auditor: alerta se a margem for menor que a mínima ou se o lucro for negativo. Lucro = preço − comissão − frete − custo. Margem = lucro ÷ preço.
A4: Frete: valores de exemplo (o CSV não traz o frete; o auditor real consulta a API do Mercado Livre). Preço e comissão vêm do CSV.
A5: Cores: azul = valor digitado · verde = puxado da aba Custos · preto = fórmula. Para usar seus próprios produtos, substitua o conteúdo da aba Custos.
A7: Margem mínima (MARGEM_MIN_PCT) | B7: 0.1
A9: SKU | B9: Produto | C9: Preço (R$) | D9: Comissão (R$) | E9: Frete exemplo (R$) | F9: Custo (R$) | G9: Lucro (R$) | H9: Margem | I9: Resultado | J9: Comentário
A10: DEMO-001 | B10: Caixa de Direção Hidráulica Modelo A 2005-2012 | C10: 520 | D10: 88.4 | E10: 38.5 | F10: =INDEX(Custos!$B$2:$B$7,MATCH(A10,Custos!$A$2:$A$7,0)) -> 290 | G10: =C10-D10-E10-F10 -> 103.1 | H10: =G10/C10 -> 0.19826923 | I10: =IF(OR(H10<$B$7,G10<0),"ALERTA","OK") -> OK | J10: Margem saudável (acima de 10%).
A11: DEMO-002 | B11: Bomba de Combustível Elétrica Modelo B | C11: 340 | D11: 57.8 | E11: 33.2 | F11: =INDEX(Custos!$B$2:$B$7,MATCH(A11,Custos!$A$2:$A$7,0)) -> 235 | G11: =C11-D11-E11-F11 -> 14 | H11: =G11/C11 -> 0.041176471 | I11: =IF(OR(H11<$B$7,G11<0),"ALERTA","OK") -> ALERTA | J11: Lucro positivo, mas margem abaixo de 10%.
A12: DEMO-003 | B12: Coxim do Motor Dianteiro Modelo C | C12: 210 | D12: 35.7 | E12: 29.9 | F12: =INDEX(Custos!$B$2:$B$7,MATCH(A12,Custos!$A$2:$A$7,0)) -> 142 | G12: =C12-D12-E12-F12 -> 2.4 | H12: =G12/C12 -> 0.011428571 | I12: =IF(OR(H12<$B$7,G12<0),"ALERTA","OK") -> ALERTA | J12: Margem quase zero: o custo consome o ganho.
A13: DEMO-004 | B13: Pastilha de Freio Dianteira Modelo D | C13: 140 | D13: 23.8 | E13: 27.4 | F13: =INDEX(Custos!$B$2:$B$7,MATCH(A13,Custos!$A$2:$A$7,0)) -> 100 | G13: =C13-D13-E13-F13 -> -11.2 | H13: =G13/C13 -> -0.08 | I13: =IF(OR(H13<$B$7,G13<0),"ALERTA","OK") -> ALERTA | J13: Prejuízo: custo maior que o que sobra após comissão e frete.
A14: DEMO-005 | B14: Kit Correia Dentada com Tensor Modelo E | C14: 280 | D14: 47.6 | E14: 34.1 | F14: =INDEX(Custos!$B$2:$B$7,MATCH(A14,Custos!$A$2:$A$7,0)) -> 165 | G14: =C14-D14-E14-F14 -> 33.3 | H14: =G14/C14 -> 0.11892857 | I14: =IF(OR(H14<$B$7,G14<0),"ALERTA","OK") -> OK | J14: Margem acima de 10%.
A15: DEMO-006 | B15: Junta da Tampa de Válvulas Modelo F | C15: 70 | D15: 11.9 | E15: 0 | F15: =INDEX(Custos!$B$2:$B$7,MATCH(A15,Custos!$A$2:$A$7,0)) -> 62 | G15: =C15-D15-E15-F15 -> -3.9 | H15: =G15/C15 -> -0.055714286 | I15: =IF(OR(H15<$B$7,G15<0),"ALERTA","OK") -> ALERTA | J15: Sem frete grátis (frete = 0), mas o custo ainda gera prejuízo.
A17: Resultado esperado: 4 produtos em ALERTA (DEMO-002, DEMO-003, DEMO-004, DEMO-006) e 2 OK (DEMO-001, DEMO-005).
